README.md
setup.cfg
setup.py
no_toplevel_code/__init__.py
no_toplevel_code/wrap.py
no_toplevel_code.egg-info/PKG-INFO
no_toplevel_code.egg-info/SOURCES.txt
no_toplevel_code.egg-info/dependency_links.txt
no_toplevel_code.egg-info/top_level.txt
tests/__init__.py
tests/utility_test.py