Metadata-Version: 2.1
Name: no-toplevel-code
Version: 1.0.0
Summary: Wrap and unwrap code to allow for modules without top-level code
Home-page: https://github.com/kavigupta/no-toplevel-code
Author: Kavi Gupta
Author-email: kavig+no_toplevel_code@mit.edu
Classifier: Programming Language :: Python :: 3.9
Classifier: Programming Language :: Python :: 3.10
Classifier: Programming Language :: Python :: 3.11
Classifier: Operating System :: OS Independent
Requires-Python: >=3.9
